AUTHORS.rst
CHANGES.rst
LICENSE.rst
MANIFEST.in
README.rst
setup.py
vero/__init__.py
vero/client.py
vero.egg-info/PKG-INFO
vero.egg-info/SOURCES.txt
vero.egg-info/dependency_links.txt
vero.egg-info/requires.txt
vero.egg-info/top_level.txt
vero.egg-info/zip-safe