Metadata-Version: 1.0
Name: vero
Version: 1.1.3
Summary: Python wrapper for Vero API
Home-page: https://github.com/waveaccounting/vero-python
Author: https://github.com/waveaccounting/vero-python/graphs/contributors
